MANIFEST.in
README.md
setup.py
dollar_ref/__init__.py
dollar_ref/console.py
dollar_ref.egg-info/PKG-INFO
dollar_ref.egg-info/SOURCES.txt
dollar_ref.egg-info/dependency_links.txt
dollar_ref.egg-info/entry_points.txt
dollar_ref.egg-info/requires.txt
dollar_ref.egg-info/top_level.txt