Metadata-Version: 1.1
Name: dollar-ref
Version: 0.1.1
Summary: JSON Reference Resolution
Home-page: https://github.com/bagrat/dollar-ref
Author: Bagrat Aznauryan
Author-email: contact@bagrat.io
License: MIT
Keywords: json schema ref reference openapi yaml resolve
Platform: UNKNOWN
Classifier: Development Status :: 3 - Alpha
Classifier: Environment :: Console
Classifier: Intended Audience :: Developers
Classifier: Intended Audience :: Information Technology
Classifier: License :: OSI Approved :: MIT License
Classifier: Programming Language :: Python :: 3.6
Classifier: Programming Language :: Python :: 3
Classifier: Programming Language :: Python :: 3 :: Only
Classifier: Topic :: Software Development
Classifier: Topic :: Software Development :: Libraries
Classifier: Topic :: Software Development :: Libraries :: Python Modules
Classifier: Topic :: Utilities
